[
{
    "originalName": "images.json",
    "title": "Please update title for image images in file images.json",
    "height": "0 cm",
    "width": "0 cm",
    "price": 0
},
{
    "originalName": "IMG_6154.JPG",
    "title": "Augusta och Hektor",
    "height": "0 cm",
    "width": "0 cm",
    "price": 0
},
{
    "originalName": "IMG_6155.JPG",
    "title": "Please update title for image IMG_6155 in file images.json",
    "height": "0 cm",
    "width": "0 cm",
    "price": 0
},
{
    "originalName": "IMG_6127.JPG",
    "title": "Please update title for image IMG_6127 in file images.json",
    "height": "0 cm",
    "width": "0 cm",
    "price": 0
},
{
    "originalName": "IMG_6162.JPG",
    "title": "Please update title for image IMG_6162 in file images.json",
    "height": "0 cm",
    "width": "0 cm",
    "price": 0
},
{
    "originalName": "IMG_6161.JPG",
    "title": "Please update title for image IMG_6161 in file images.json",
    "height": "0 cm",
    "width": "0 cm",
    "price": 0
},
{
    "originalName": "IMG_6114.JPG",
    "title": "Please update title for image IMG_6114 in file images.json",
    "height": "0 cm",
    "width": "0 cm",
    "price": 0
},
{
    "originalName": "IMG_6159.JPG",
    "title": "Please update title for image IMG_6159 in file images.json",
    "height": "0 cm",
    "width": "0 cm",
    "price": 0
},
{
    "originalName": "IMG_6182.JPG",
    "title": "Please update title for image IMG_6182 in file images.json",
    "height": "0 cm",
    "width": "0 cm",
    "price": 0
},
{
    "originalName": "IMG_6193.JPG",
    "title": "Please update title for image IMG_6193 in file images.json",
    "height": "0 cm",
    "width": "0 cm",
    "price": 0
},
{
    "originalName": "IMG_6117.JPG",
    "title": "Please update title for image IMG_6117 in file images.json",
    "height": "0 cm",
    "width": "0 cm",
    "price": 0
},
{
    "originalName": "IMG_6116.JPG",
    "title": "Please update title for image IMG_6116 in file images.json",
    "height": "0 cm",
    "width": "0 cm",
    "price": 0
},
{
    "originalName": "IMG_6153.JPG",
    "title": "Please update title for image IMG_6153 in file images.json",
    "height": "0 cm",
    "width": "0 cm",
    "price": 0
},
{
    "originalName": "IMG_6191.JPG",
    "title": "Please update title for image IMG_6191 in file images.json",
    "height": "0 cm",
    "width": "0 cm",
    "price": 0
},
{
    "originalName": "IMG_6198.JPG",
    "title": "Please update title for image IMG_6198 in file images.json",
    "height": "0 cm",
    "width": "0 cm",
    "price": 0
},
{
    "originalName": "IMG_6115.JPG",
    "title": "Please update title for image IMG_6115 in file images.json",
    "height": "0 cm",
    "width": "0 cm",
    "price": 0
},
{
    "originalName": "IMG_6122.JPG",
    "title": "Please update title for image IMG_6122 in file images.json",
    "height": "0 cm",
    "width": "0 cm",
    "price": 0
},
{
    "originalName": "IMG_6131.JPG",
    "title": "Please update title for image IMG_6131 in file images.json",
    "height": "0 cm",
    "width": "0 cm",
    "price": 0
},
{
    "originalName": "IMG_6151.JPG",
    "title": "Please update title for image IMG_6151 in file images.json",
    "height": "0 cm",
    "width": "0 cm",
    "price": 0
},
{
    "originalName": "IMG_6166.JPG",
    "title": "Please update title for image IMG_6166 in file images.json",
    "height": "0 cm",
    "width": "0 cm",
    "price": 0
},
{
    "originalName": "IMG_6167.JPG",
    "title": "Please update title for image IMG_6167 in file images.json",
    "height": "0 cm",
    "width": "0 cm",
    "price": 0
},
{
    "originalName": "IMG_6173.JPG",
    "title": "Please update title for image IMG_6173 in file images.json",
    "height": "0 cm",
    "width": "0 cm",
    "price": 0
},
{
    "originalName": "IMG_6180.JPG",
    "title": "Please update title for image IMG_6180 in file images.json",
    "height": "0 cm",
    "width": "0 cm",
    "price": 0
},
{
    "originalName": "IMG_6181.JPG",
    "title": "Please update title for image IMG_6181 in file images.json",
    "height": "0 cm",
    "width": "0 cm",
    "price": 0
},
{
    "originalName": "IMG_6192.JPG",
    "title": "Please update title for image IMG_6192 in file images.json",
    "height": "0 cm",
    "width": "0 cm",
    "price": 0
},
{
    "originalName": "IMG_6129.JPG",
    "title": "Please update title for image IMG_6129 in file images.json",
    "height": "0 cm",
    "width": "0 cm",
    "price": 0
},
{
    "originalName": "IMG_6152.JPG",
    "title": "Please update title for image IMG_6152 in file images.json",
    "height": "0 cm",
    "width": "0 cm",
    "price": 0
},
{
    "originalName": "IMG_6156.JPG",
    "title": "Please update title for image IMG_6156 in file images.json",
    "height": "0 cm",
    "width": "0 cm",
    "price": 0
},
{
    "originalName": "IMG_6158.JPG",
    "title": "Please update title for image IMG_6158 in file images.json",
    "height": "0 cm",
    "width": "0 cm",
    "price": 0
},
{
    "originalName": "IMG_6179.JPG",
    "title": "Please update title for image IMG_6179 in file images.json",
    "height": "0 cm",
    "width": "0 cm",
    "price": 0
},
{
    "originalName": "IMG_6188.JPG",
    "title": "Please update title for image IMG_6188 in file images.json",
    "height": "0 cm",
    "width": "0 cm",
    "price": 0
},
{
    "originalName": "IMG_6189.JPG",
    "title": "Please update title for image IMG_6189 in file images.json",
    "height": "0 cm",
    "width": "0 cm",
    "price": 0
},
{
    "originalName": "IMG_6128.JPG",
    "title": "Please update title for image IMG_6128 in file images.json",
    "height": "0 cm",
    "width": "0 cm",
    "price": 0
},
{
    "originalName": "IMG_6134.JPG",
    "title": "Please update title for image IMG_6134 in file images.json",
    "height": "0 cm",
    "width": "0 cm",
    "price": 0
},
{
    "originalName": "IMG_6163.JPG",
    "title": "Please update title for image IMG_6163 in file images.json",
    "height": "0 cm",
    "width": "0 cm",
    "price": 0
},
{
    "originalName": "IMG_6171.JPG",
    "title": "Please update title for image IMG_6171 in file images.json",
    "height": "0 cm",
    "width": "0 cm",
    "price": 0
},
{
    "originalName": "IMG_6178.JPG",
    "title": "Please update title for image IMG_6178 in file images.json",
    "height": "0 cm",
    "width": "0 cm",
    "price": 0
},
{
    "originalName": "IMG_6177.JPG",
    "title": "Please update title for image IMG_6177 in file images.json",
    "height": "0 cm",
    "width": "0 cm",
    "price": 0
},
{
    "originalName": "IMG_6199.JPG",
    "title": "Please update title for image IMG_6199 in file images.json",
    "height": "0 cm",
    "width": "0 cm",
    "price": 0
},
{
    "originalName": "IMG_6133.JPG",
    "title": "Please update title for image IMG_6133 in file images.json",
    "height": "0 cm",
    "width": "0 cm",
    "price": 0
},
{
    "originalName": "IMG_6160.JPG",
    "title": "Please update title for image IMG_6160 in file images.json",
    "height": "0 cm",
    "width": "0 cm",
    "price": 0
},
{
    "originalName": "IMG_6172.JPG",
    "title": "Please update title for image IMG_6172 in file images.json",
    "height": "0 cm",
    "width": "0 cm",
    "price": 0
},
{
    "originalName": "IMG_6130.JPG",
    "title": "Please update title for image IMG_6130 in file images.json",
    "height": "0 cm",
    "width": "0 cm",
    "price": 0
},
{
    "originalName": "IMG_6157.JPG",
    "title": "Please update title for image IMG_6157 in file images.json",
    "height": "0 cm",
    "width": "0 cm",
    "price": 0
},
{
    "originalName": "IMG_6149.JPG",
    "title": "Please update title for image IMG_6149 in file images.json",
    "height": "0 cm",
    "width": "0 cm",
    "price": 0
},
{
    "originalName": "IMG_6165.JPG",
    "title": "Please update title for image IMG_6165 in file images.json",
    "height": "0 cm",
    "width": "0 cm",
    "price": 0
},
{
    "originalName": "IMG_6103.JPG",
    "title": "Please update title for image IMG_6103 in file images.json",
    "height": "0 cm",
    "width": "0 cm",
    "price": 0
},
{
    "originalName": "IMG_6104.JPG",
    "title": "Please update title for image IMG_6104 in file images.json",
    "height": "0 cm",
    "width": "0 cm",
    "price": 0
},
{
    "originalName": "IMG_6105.JPG",
    "title": "Please update title for image IMG_6105 in file images.json",
    "height": "0 cm",
    "width": "0 cm",
    "price": 0
},
{
    "originalName": "IMG_6138.JPG",
    "title": "Please update title for image IMG_6138 in file images.json",
    "height": "0 cm",
    "width": "0 cm",
    "price": 0
},
{
    "originalName": "IMG_6164.JPG",
    "title": "Please update title for image IMG_6164 in file images.json",
    "height": "0 cm",
    "width": "0 cm",
    "price": 0
},
{
    "originalName": "IMG_6169.JPG",
    "title": "Please update title for image IMG_6169 in file images.json",
    "height": "0 cm",
    "width": "0 cm",
    "price": 0
},
{
    "originalName": "IMG_6124.JPG",
    "title": "Please update title for image IMG_6124 in file images.json",
    "height": "0 cm",
    "width": "0 cm",
    "price": 0
},
{
    "originalName": "IMG_6139.JPG",
    "title": "Please update title for image IMG_6139 in file images.json",
    "height": "0 cm",
    "width": "0 cm",
    "price": 0
},
{
    "originalName": "IMG_6135.JPG",
    "title": "Please update title for image IMG_6135 in file images.json",
    "height": "0 cm",
    "width": "0 cm",
    "price": 0
},
{
    "originalName": "IMG_6143.JPG",
    "title": "Please update title for image IMG_6143 in file images.json",
    "height": "0 cm",
    "width": "0 cm",
    "price": 0
},
{
    "originalName": "IMG_6147.JPG",
    "title": "Please update title for image IMG_6147 in file images.json",
    "height": "0 cm",
    "width": "0 cm",
    "price": 0
},
{
    "originalName": "IMG_6148.JPG",
    "title": "Please update title for image IMG_6148 in file images.json",
    "height": "0 cm",
    "width": "0 cm",
    "price": 0
},
{
    "originalName": "IMG_6123.JPG",
    "title": "Please update title for image IMG_6123 in file images.json",
    "height": "0 cm",
    "width": "0 cm",
    "price": 0
},
{
    "originalName": "IMG_6132.JPG",
    "title": "Please update title for image IMG_6132 in file images.json",
    "height": "0 cm",
    "width": "0 cm",
    "price": 0
},
{
    "originalName": "IMG_60.JPG",
    "title": "Please update title for image IMG_60 in file images.json",
    "height": "0 cm",
    "width": "0 cm",
    "price": 0
},
{
    "originalName": "IMG_6126.JPG",
    "title": "Please update title for image IMG_6126 in file images.json",
    "height": "0 cm",
    "width": "0 cm",
    "price": 0
},
{
    "originalName": "IMG_6102.JPG",
    "title": "Please update title for image IMG_6102 in file images.json",
    "height": "0 cm",
    "width": "0 cm",
    "price": 0
},
{
    "originalName": "IMG_6107.JPG",
    "title": "Please update title for image IMG_6107 in file images.json",
    "height": "0 cm",
    "width": "0 cm",
    "price": 0
},
{
    "originalName": "IMG_6145.JPG",
    "title": "Please update title for image IMG_6145 in file images.json",
    "height": "0 cm",
    "width": "0 cm",
    "price": 0
},
{
    "originalName": "IMG_6125.JPG",
    "title": "Please update title for image IMG_6125 in file images.json",
    "height": "0 cm",
    "width": "0 cm",
    "price": 0
},
{
    "originalName": "IMG_6175.JPG",
    "title": "Please update title for image IMG_6175 in file images.json",
    "height": "0 cm",
    "width": "0 cm",
    "price": 0
},
{
    "originalName": "IMG_6176.JPG",
    "title": "Please update title for image IMG_6176 in file images.json",
    "height": "0 cm",
    "width": "0 cm",
    "price": 0
},
{
    "originalName": "IMG_6101.JPG",
    "title": "Please update title for image IMG_6101 in file images.json",
    "height": "0 cm",
    "width": "0 cm",
    "price": 0
},
{
    "originalName": "IMG_6111.JPG",
    "title": "Please update title for image IMG_6111 in file images.json",
    "height": "0 cm",
    "width": "0 cm",
    "price": 0
},
{
    "originalName": "IMG_6137.JPG",
    "title": "Please update title for image IMG_6137 in file images.json",
    "height": "0 cm",
    "width": "0 cm",
    "price": 0
},
{
    "originalName": "IMG_6140.JPG",
    "title": "Please update title for image IMG_6140 in file images.json",
    "height": "0 cm",
    "width": "0 cm",
    "price": 0
},
{
    "originalName": "IMG_6195.JPG",
    "title": "Please update title for image IMG_6195 in file images.json",
    "height": "0 cm",
    "width": "0 cm",
    "price": 0
},
{
    "originalName": "IMG_6142.JPG",
    "title": "Please update title for image IMG_6142 in file images.json",
    "height": "0 cm",
    "width": "0 cm",
    "price": 0
},
{
    "originalName": "IMG_6168.JPG",
    "title": "Please update title for image IMG_6168 in file images.json",
    "height": "0 cm",
    "width": "0 cm",
    "price": 0
},
{
    "originalName": "IMG_6136.JPG",
    "title": "Please update title for image IMG_6136 in file images.json",
    "height": "0 cm",
    "width": "0 cm",
    "price": 0
},
{
    "originalName": "IMG_6141.JPG",
    "title": "Please update title for image IMG_6141 in file images.json",
    "height": "0 cm",
    "width": "0 cm",
    "price": 0
},
{
    "originalName": "IMG_6146.JPG",
    "title": "Please update title for image IMG_6146 in file images.json",
    "height": "0 cm",
    "width": "0 cm",
    "price": 0
},
{
    "originalName": "IMG_6183.JPG",
    "title": "Please update title for image IMG_6183 in file images.json",
    "height": "0 cm",
    "width": "0 cm",
    "price": 0
},
{
    "originalName": "IMG_6174.JPG",
    "title": "Please update title for image IMG_6174 in file images.json",
    "height": "0 cm",
    "width": "0 cm",
    "price": 0
},
{
    "originalName": "IMG_6144.JPG",
    "title": "Please update title for image IMG_6144 in file images.json",
    "height": "0 cm",
    "width": "0 cm",
    "price": 0
}
]
